README.txt
pypi_upload.sh
setup.cfg
setup.py
docs/HISTORY.txt
docs/INSTALL.txt
docs/LICENSE.GPL
docs/LICENSE.txt
upc/__init__.py
upc.remotecontrol.egg-info/PKG-INFO
upc.remotecontrol.egg-info/SOURCES.txt
upc.remotecontrol.egg-info/dependency_links.txt
upc.remotecontrol.egg-info/entry_points.txt
upc.remotecontrol.egg-info/namespace_packages.txt
upc.remotecontrol.egg-info/not-zip-safe
upc.remotecontrol.egg-info/paster_plugins.txt
upc.remotecontrol.egg-info/requires.txt
upc.remotecontrol.egg-info/top_level.txt
upc/remotecontrol/README.txt
upc/remotecontrol/__init__.py
upc/remotecontrol/configure.zcml
upc/remotecontrol/tests.py
upc/remotecontrol/browser/__init__.py
upc/remotecontrol/browser/configure.zcml
upc/remotecontrol/browser/remotecontrol.py