Metadata-Version: 1.0
Name: upc.remotecontrol
Version: 1.0a1
Summary: UNKNOWN
Home-page: UNKNOWN
Author: Timo Stollenwerk
Author-email: timo@zmag.de
License: GPL
Platform: UNKNOWN
Classifier: Framework :: Plone
Classifier: Programming Language :: Python
